metastore/__init__.py
metastore/types.py
metastore/util.py
metastore/backend/__init__.py
metastore/backend/exc.py
metastore/backend/filesystem.py
metastore/backend/git_lfs_helpers.py
metastore/backend/github/__init__.py
metastore/backend/github/gh_rest_api.py
metastore/backend/github/storage.py
tests/__init__.py
tests/test_base.py
tests/backend/__init__.py
tests/backend/test_filesystem_backend.py
tests/backend/test_git_lfs_helpers.py
tests/backend/test_github_backend.py
metastore_lib-0.2.0.dist-info/LICENSE
metastore_lib-0.2.0.dist-info/METADATA
metastore_lib-0.2.0.dist-info/WHEEL
metastore_lib-0.2.0.dist-info/top_level.txt
metastore_lib-0.2.0.dist-info/RECORD
