Metadata-Version: 2.1
Name: metastore-lib
Version: 0.2.0
Summary: A library for abstracting versioned metadata storage for data packages
Home-page: UNKNOWN
Author: Shahar Evron
Author-email: shahar.evron@datopian.com
License: UNKNOWN
Platform: UNKNOWN
Requires-Dist: pytz
Requires-Dist: six
Requires-Dist: typing
Requires-Dist: typing-extensions
Requires-Dist: python-dateutil (>=2.7.0)
Requires-Dist: fs
Requires-Dist: pygithub
